deep_xf/__init__.py
deep_xf/denoise.py
deep_xf/dpp.py
deep_xf/forecast_ml.py
deep_xf/forecast_ml_extension.py
deep_xf/gnn_layer.py
deep_xf/main.py
deep_xf/similarity.py
deep_xf/stats.py
deep_xf/utility.py
deep_xf-0.0.5.dist-info/METADATA
deep_xf-0.0.5.dist-info/WHEEL
deep_xf-0.0.5.dist-info/top_level.txt
deep_xf-0.0.5.dist-info/RECORD
