Metadata-Version: 2.1
Name: deep-xf
Version: 0.0.5
Summary: DEEPXF - An open-source, low-code explainable forecasting and nowcasting library with state-of-the-art deep neural networks and Dynamic Factor Model. Now available with additional addons like Denoising TS signals with ensembling of filters, TS signal similarity test with Siamese Neural Networks
Home-page: https://github.com/ajayarunachalam/Deep_XF
Author: Ajay Arunachalam
Author-email: ajay.arunachalam08@gmail.com
License: MIT
Platform: UNKNOWN
Requires-Dist: ipython
Requires-Dist: jupyter
Requires-Dist: tqdm
Requires-Dist: pandas
Requires-Dist: matplotlib
Requires-Dist: seaborn (==0.9.0)
Requires-Dist: scikit-learn (>=0.24.0)
Requires-Dist: pandas-profiling
Requires-Dist: statsmodels (==0.12.2)
Requires-Dist: keras
Requires-Dist: torch
Requires-Dist: shap (==0.39.0)
Requires-Dist: py-ecg-detectors
